python_starter
