Metadata-Version: 1.1
Name: python-starter
Version: 0.2.0
Summary: 'module-starter' for Python
Home-page: https://github.com/koji-kojiro/python-starter
Author: Kojiro TANI
Author-email: kojiro0531@gmail.com
License: MIT
Platform: UNKNOWN
Classifier: Programming Language :: Python
Classifier: Programming Language :: Python :: 2
Classifier: Programming Language :: Python :: 3
Classifier: Natural Language :: English
Classifier: License :: OSI Approved :: MIT License
Classifier: Intended Audience :: Developers
Classifier: Topic :: Software Development
Classifier: Environment :: Console
Classifier: Development Status :: 4 - Beta
